{
  "university": {
    "type": "university",
    "university_id": "unipa",
    "name": "Università degli Studi di Palermo",
    "official_url": "https://www.unipa.it",
    "country": "Italy",
    "city": "Palermo",
    "campuses": [
      {"city": "Palermo", "address": "Piazza Marina 61", "notes": "Main campus"},
      {"city": "Agrigento", "address": "", "notes": "Polo didattico"},
      {"city": "Caltanissetta", "address": "", "notes": "Polo didattico"},
      {"city": "Trapani", "address": "", "notes": "Polo didattico"}
    ],
    "languages_offered": ["Italian", "English"],
    "contacts": {"email": "urp@unipa.it", "phone": "+39 091 238 111", "address": "Piazza Marina 61, 90133 Palermo"},
    "source_url": "https://www.unipa.it",
    "last_checked": "2026-01-05",
    "confidence": 0.95,
    "notes": "Major Sicilian university. 161 degree programs: 75 bachelor, 76 master, 10 ciclo unico. 45,000+ students. No tax area €25,000. ERSU Palermo regional scholarships."
  },
  "programs": [
    {"type":"program","university_id":"unipa","degree_level":"bachelor","program_name":"Scienze Biologiche","class_code":"L-13","language":["Italian"],"campus_city":"Palermo","duration_years":3,"ects_total":180,"source_url":"https://www.unipa.it","last_checked":"2026-01-05","confidence":0.9,"notes":""},
    {"type":"program","university_id":"unipa","degree_level":"bachelor","program_name":"Biotecnologie","class_code":"L-2","language":["Italian"],"campus_city":"Palermo","duration_years":3,"ects_total":180,"source_url":"https://www.unipa.it","last_checked":"2026-01-05","confidence":0.9,"notes":""},
    {"type":"program","university_id":"unipa","degree_level":"bachelor","program_name":"Chimica","class_code":"L-27","language":["Italian"],"campus_city":"Palermo","duration_years":3,"ects_total":180,"source_url":"https://www.unipa.it","last_checked":"2026-01-05","confidence":0.9,"notes":""},
    {"type":"program","university_id":"unipa","degree_level":"bachelor","program_name":"Fisica","class_code":"L-30","language":["Italian"],"campus_city":"Palermo","duration_years":3,"ects_total":180,"source_url":"https://www.unipa.it","last_checked":"2026-01-05","confidence":0.9,"notes":""},
    {"type":"program","university_id":"unipa","degree_level":"bachelor","program_name":"Informatica","class_code":"L-31","language":["Italian"],"campus_city":"Palermo","duration_years":3,"ects_total":180,"source_url":"https://www.unipa.it","last_checked":"2026-01-05","confidence":0.9,"notes":""},
    {"type":"program","university_id":"unipa","degree_level":"bachelor","program_name":"Matematica","class_code":"L-35","language":["Italian"],"campus_city":"Palermo","duration_years":3,"ects_total":180,"source_url":"https://www.unipa.it","last_checked":"2026-01-05","confidence":0.9,"notes":""},
    {"type":"program","university_id":"unipa","degree_level":"bachelor","program_name":"Scienze Geologiche","class_code":"L-34","language":["Italian"],"campus_city":"Palermo","duration_years":3,"ects_total":180,"source_url":"https://www.unipa.it","last_checked":"2026-01-05","confidence":0.9,"notes":""},
    {"type":"program","university_id":"unipa","degree_level":"bachelor","program_name":"Scienze della Natura e dell'Ambiente","class_code":"L-32","language":["Italian"],"campus_city":"Palermo","duration_years":3,"ects_total":180,"source_url":"https://www.unipa.it","last_checked":"2026-01-05","confidence":0.9,"notes":""},
    {"type":"program","university_id":"unipa","degree_level":"bachelor","program_name":"Statistica per l'Analisi dei Dati","class_code":"L-41","language":["Italian"],"campus_city":"Palermo","duration_years":3,"ects_total":180,"source_url":"https://www.unipa.it","last_checked":"2026-01-05","confidence":0.9,"notes":""},
    {"type":"program","university_id":"unipa","degree_level":"bachelor","program_name":"Economia e Amministrazione Aziendale","class_code":"L-18","language":["Italian"],"campus_city":"Palermo","duration_years":3,"ects_total":180,"source_url":"https://www.unipa.it","last_checked":"2026-01-05","confidence":0.9,"notes":""},
    {"type":"program","university_id":"unipa","degree_level":"bachelor","program_name":"Economia e Finanza","class_code":"L-33","language":["Italian"],"campus_city":"Palermo","duration_years":3,"ects_total":180,"source_url":"https://www.unipa.it","last_checked":"2026-01-05","confidence":0.9,"notes":""},
    {"type":"program","university_id":"unipa","degree_level":"bachelor","program_name":"Scienze del Turismo","class_code":"L-15","language":["Italian"],"campus_city":"Palermo","duration_years":3,"ects_total":180,"source_url":"https://www.unipa.it","last_checked":"2026-01-05","confidence":0.9,"notes":""},
    {"type":"program","university_id":"unipa","degree_level":"bachelor","program_name":"Ingegneria Biomedica","class_code":"L-8","language":["Italian"],"campus_city":"Palermo","duration_years":3,"ects_total":180,"source_url":"https://www.unipa.it","last_checked":"2026-01-05","confidence":0.9,"notes":""},
    {"type":"program","university_id":"unipa","degree_level":"bachelor","program_name":"Ingegneria Chimica","class_code":"L-9","language":["Italian"],"campus_city":"Palermo","duration_years":3,"ects_total":180,"source_url":"https://www.unipa.it","last_checked":"2026-01-05","confidence":0.9,"notes":""},
    {"type":"program","university_id":"unipa","degree_level":"bachelor","program_name":"Ingegneria Civile","class_code":"L-7","language":["Italian"],"campus_city":"Palermo","duration_years":3,"ects_total":180,"source_url":"https://www.unipa.it","last_checked":"2026-01-05","confidence":0.9,"notes":""},
    {"type":"program","university_id":"unipa","degree_level":"bachelor","program_name":"Ingegneria Civile","class_code":"L-7","language":["Italian"],"campus_city":"Agrigento","duration_years":3,"ects_total":180,"source_url":"https://www.unipa.it","last_checked":"2026-01-05","confidence":0.9,"notes":"Polo Agrigento"},
    {"type":"program","university_id":"unipa","degree_level":"bachelor","program_name":"Ingegneria dell'Innovazione per le Imprese Digitali","class_code":"L-8","language":["Italian"],"campus_city":"Palermo","duration_years":3,"ects_total":180,"source_url":"https://www.unipa.it","last_checked":"2026-01-05","confidence":0.9,"notes":""},
    {"type":"program","university_id":"unipa","degree_level":"bachelor","program_name":"Ingegneria Elettrica ed Elettronica","class_code":"L-8","language":["Italian"],"campus_city":"Palermo","duration_years":3,"ects_total":180,"source_url":"https://www.unipa.it","last_checked":"2026-01-05","confidence":0.9,"notes":""},
    {"type":"program","university_id":"unipa","degree_level":"bachelor","program_name":"Ingegneria Elettronica","class_code":"L-8","language":["Italian"],"campus_city":"Palermo","duration_years":3,"ects_total":180,"source_url":"https://www.unipa.it","last_checked":"2026-01-05","confidence":0.9,"notes":""},
    {"type":"program","university_id":"unipa","degree_level":"bachelor","program_name":"Ingegneria Gestionale","class_code":"L-9","language":["Italian"],"campus_city":"Palermo","duration_years":3,"ects_total":180,"source_url":"https://www.unipa.it","last_checked":"2026-01-05","confidence":0.9,"notes":""},
    {"type":"program","university_id":"unipa","degree_level":"bachelor","program_name":"Ingegneria Informatica","class_code":"L-8","language":["Italian"],"campus_city":"Palermo","duration_years":3,"ects_total":180,"source_url":"https://www.unipa.it","last_checked":"2026-01-05","confidence":0.9,"notes":""},
    {"type":"program","university_id":"unipa","degree_level":"bachelor","program_name":"Ingegneria Meccanica","class_code":"L-9","language":["Italian"],"campus_city":"Palermo","duration_years":3,"ects_total":180,"source_url":"https://www.unipa.it","last_checked":"2026-01-05","confidence":0.9,"notes":""},
    {"type":"program","university_id":"unipa","degree_level":"bachelor","program_name":"Ingegneria per l'Ambiente e il Territorio","class_code":"L-7","language":["Italian"],"campus_city":"Palermo","duration_years":3,"ects_total":180,"source_url":"https://www.unipa.it","last_checked":"2026-01-05","confidence":0.9,"notes":""},
    {"type":"program","university_id":"unipa","degree_level":"bachelor","program_name":"Ingegneria Edile, Innovazione e Recupero del Costruito","class_code":"L-7","language":["Italian"],"campus_city":"Palermo","duration_years":3,"ects_total":180,"source_url":"https://www.unipa.it","last_checked":"2026-01-05","confidence":0.9,"notes":""},
    {"type":"program","university_id":"unipa","degree_level":"bachelor","program_name":"Scienze dell'Architettura","class_code":"L-17","language":["Italian"],"campus_city":"Palermo","duration_years":3,"ects_total":180,"source_url":"https://www.unipa.it","last_checked":"2026-01-05","confidence":0.9,"notes":""},
    {"type":"program","university_id":"unipa","degree_level":"bachelor","program_name":"Urbanistica e Scienze della Città","class_code":"L-21","language":["Italian"],"campus_city":"Palermo","duration_years":3,"ects_total":180,"source_url":"https://www.unipa.it","last_checked":"2026-01-05","confidence":0.9,"notes":""},
    {"type":"program","university_id":"unipa","degree_level":"bachelor","program_name":"Design e Cultura del Territorio","class_code":"L-4","language":["Italian"],"campus_city":"Palermo","duration_years":3,"ects_total":180,"source_url":"https://www.unipa.it","last_checked":"2026-01-05","confidence":0.9,"notes":""},
    {"type":"program","university_id":"unipa","degree_level":"bachelor","program_name":"Filosofia","class_code":"L-5","language":["Italian"],"campus_city":"Palermo","duration_years":3,"ects_total":180,"source_url":"https://www.unipa.it","last_checked":"2026-01-05","confidence":0.9,"notes":""},
    {"type":"program","university_id":"unipa","degree_level":"bachelor","program_name":"Lettere","class_code":"L-10","language":["Italian"],"campus_city":"Palermo","duration_years":3,"ects_total":180,"source_url":"https://www.unipa.it","last_checked":"2026-01-05","confidence":0.9,"notes":""},
    {"type":"program","university_id":"unipa","degree_level":"bachelor","program_name":"Storia","class_code":"L-42","language":["Italian"],"campus_city":"Palermo","duration_years":3,"ects_total":180,"source_url":"https://www.unipa.it","last_checked":"2026-01-05","confidence":0.9,"notes":""},
    {"type":"program","university_id":"unipa","degree_level":"bachelor","program_name":"Beni Culturali","class_code":"L-1","language":["Italian"],"campus_city":"Palermo","duration_years":3,"ects_total":180,"source_url":"https://www.unipa.it","last_checked":"2026-01-05","confidence":0.9,"notes":""},
    {"type":"program","university_id":"unipa","degree_level":"bachelor","program_name":"Beni Culturali","class_code":"L-1","language":["Italian"],"campus_city":"Agrigento","duration_years":3,"ects_total":180,"source_url":"https://www.unipa.it","last_checked":"2026-01-05","confidence":0.9,"notes":"Polo Agrigento"},
    {"type":"program","university_id":"unipa","degree_level":"bachelor","program_name":"Discipline delle Arti, della Musica e dello Spettacolo","class_code":"L-3","language":["Italian"],"campus_city":"Palermo","duration_years":3,"ects_total":180,"source_url":"https://www.unipa.it","last_checked":"2026-01-05","confidence":0.9,"notes":""},
    {"type":"program","university_id":"unipa","degree_level":"bachelor","program_name":"Studi Filosofici e Storici","class_code":"L-5","language":["Italian"],"campus_city":"Palermo","duration_years":3,"ects_total":180,"source_url":"https://www.unipa.it","last_checked":"2026-01-05","confidence":0.9,"notes":""},
    {"type":"program","university_id":"unipa","degree_level":"bachelor","program_name":"Lingue e Letterature - Studi Interculturali","class_code":"L-11","language":["Italian"],"campus_city":"Palermo","duration_years":3,"ects_total":180,"source_url":"https://www.unipa.it","last_checked":"2026-01-05","confidence":0.9,"notes":""},
    {"type":"program","university_id":"unipa","degree_level":"bachelor","program_name":"Mediazione Linguistica e Italiano come Lingua Seconda","class_code":"L-12","language":["Italian"],"campus_city":"Palermo","duration_years":3,"ects_total":180,"source_url":"https://www.unipa.it","last_checked":"2026-01-05","confidence":0.9,"notes":""},
    {"type":"program","university_id":"unipa","degree_level":"bachelor","program_name":"Comunicazione Pubblica","class_code":"L-20","language":["Italian"],"campus_city":"Palermo","duration_years":3,"ects_total":180,"source_url":"https://www.unipa.it","last_checked":"2026-01-05","confidence":0.9,"notes":""},
    {"type":"program","university_id":"unipa","degree_level":"bachelor","program_name":"Scienze e Tecniche Psicologiche","class_code":"L-24","language":["Italian"],"campus_city":"Palermo","duration_years":3,"ects_total":180,"source_url":"https://www.unipa.it","last_checked":"2026-01-05","confidence":0.9,"notes":""},
    {"type":"program","university_id":"unipa","degree_level":"bachelor","program_name":"Scienze dell'Educazione","class_code":"L-19","language":["Italian"],"campus_city":"Palermo","duration_years":3,"ects_total":180,"source_url":"https://www.unipa.it","last_checked":"2026-01-05","confidence":0.9,"notes":""},
    {"type":"program","university_id":"unipa","degree_level":"bachelor","program_name":"Scienze dell'Educazione","class_code":"L-19","language":["Italian"],"campus_city":"Agrigento","duration_years":3,"ects_total":180,"source_url":"https://www.unipa.it","last_checked":"2026-01-05","confidence":0.9,"notes":"Polo Agrigento"},
    {"type":"program","university_id":"unipa","degree_level":"bachelor","program_name":"Scienze Politiche e delle Relazioni Internazionali","class_code":"L-36","language":["Italian"],"campus_city":"Palermo","duration_years":3,"ects_total":180,"source_url":"https://www.unipa.it","last_checked":"2026-01-05","confidence":0.9,"notes":""},
    {"type":"program","university_id":"unipa","degree_level":"bachelor","program_name":"Servizio Sociale","class_code":"L-39","language":["Italian"],"campus_city":"Palermo","duration_years":3,"ects_total":180,"source_url":"https://www.unipa.it","last_checked":"2026-01-05","confidence":0.9,"notes":""},
    {"type":"program","university_id":"unipa","degree_level":"bachelor","program_name":"Sviluppo Economico, Cooperazione Internazionale e Migrazioni","class_code":"L-37","language":["Italian"],"campus_city":"Palermo","duration_years":3,"ects_total":180,"source_url":"https://www.unipa.it","last_checked":"2026-01-05","confidence":0.9,"notes":""},
    {"type":"program","university_id":"unipa","degree_level":"bachelor","program_name":"Scienze Motorie e Sportive","class_code":"L-22","language":["Italian"],"campus_city":"Palermo","duration_years":3,"ects_total":180,"source_url":"https://www.unipa.it","last_checked":"2026-01-05","confidence":0.9,"notes":""},
    {"type":"program","university_id":"unipa","degree_level":"bachelor","program_name":"Scienze e Tecnologie Agrarie","class_code":"L-25","language":["Italian"],"campus_city":"Palermo","duration_years":3,"ects_total":180,"source_url":"https://www.unipa.it","last_checked":"2026-01-05","confidence":0.9,"notes":""},
    {"type":"program","university_id":"unipa","degree_level":"bachelor","program_name":"Scienze e Tecnologie Agroalimentari","class_code":"L-26","language":["Italian"],"campus_city":"Palermo","duration_years":3,"ects_total":180,"source_url":"https://www.unipa.it","last_checked":"2026-01-05","confidence":0.9,"notes":""},
    {"type":"program","university_id":"unipa","degree_level":"bachelor","program_name":"Scienze Forestali e Ambientali","class_code":"L-25","language":["Italian"],"campus_city":"Palermo","duration_years":3,"ects_total":180,"source_url":"https://www.unipa.it","last_checked":"2026-01-05","confidence":0.9,"notes":""},
    {"type":"program","university_id":"unipa","degree_level":"bachelor","program_name":"Viticoltura ed Enologia","class_code":"L-26","language":["Italian"],"campus_city":"Palermo","duration_years":3,"ects_total":180,"source_url":"https://www.unipa.it","last_checked":"2026-01-05","confidence":0.9,"notes":""},
    {"type":"program","university_id":"unipa","degree_level":"bachelor","program_name":"Infermieristica","class_code":"L/SNT1","language":["Italian"],"campus_city":"Palermo","duration_years":3,"ects_total":180,"source_url":"https://www.unipa.it","last_checked":"2026-01-05","confidence":0.9,"notes":"Healthcare profession"},
    {"type":"program","university_id":"unipa","degree_level":"bachelor","program_name":"Fisioterapia","class_code":"L/SNT2","language":["Italian"],"campus_city":"Palermo","duration_years":3,"ects_total":180,"source_url":"https://www.unipa.it","last_checked":"2026-01-05","confidence":0.9,"notes":"Healthcare profession"},
    {"type":"program","university_id":"unipa","degree_level":"bachelor","program_name":"Logopedia","class_code":"L/SNT2","language":["Italian"],"campus_city":"Palermo","duration_years":3,"ects_total":180,"source_url":"https://www.unipa.it","last_checked":"2026-01-05","confidence":0.9,"notes":"Healthcare profession"},
    {"type":"program","university_id":"unipa","degree_level":"bachelor","program_name":"Ostetricia","class_code":"L/SNT1","language":["Italian"],"campus_city":"Palermo","duration_years":3,"ects_total":180,"source_url":"https://www.unipa.it","last_checked":"2026-01-05","confidence":0.9,"notes":"Healthcare profession"},
    {"type":"program","university_id":"unipa","degree_level":"bachelor","program_name":"Tecniche di Laboratorio Biomedico","class_code":"L/SNT3","language":["Italian"],"campus_city":"Palermo","duration_years":3,"ects_total":180,"source_url":"https://www.unipa.it","last_checked":"2026-01-05","confidence":0.9,"notes":"Healthcare profession"},
    {"type":"program","university_id":"unipa","degree_level":"bachelor","program_name":"Tecniche di Radiologia Medica","class_code":"L/SNT3","language":["Italian"],"campus_city":"Palermo","duration_years":3,"ects_total":180,"source_url":"https://www.unipa.it","last_checked":"2026-01-05","confidence":0.9,"notes":"Healthcare profession"},
    {"type":"program","university_id":"unipa","degree_level":"bachelor","program_name":"Dietistica","class_code":"L/SNT3","language":["Italian"],"campus_city":"Palermo","duration_years":3,"ects_total":180,"source_url":"https://www.unipa.it","last_checked":"2026-01-05","confidence":0.9,"notes":"Healthcare profession"},
    {"type":"program","university_id":"unipa","degree_level":"bachelor","program_name":"Tecnica della Riabilitazione Psichiatrica","class_code":"L/SNT2","language":["Italian"],"campus_city":"Palermo","duration_years":3,"ects_total":180,"source_url":"https://www.unipa.it","last_checked":"2026-01-05","confidence":0.9,"notes":"Healthcare profession"},
    {"type":"program","university_id":"unipa","degree_level":"bachelor","program_name":"Assistenza Sanitaria","class_code":"L/SNT4","language":["Italian"],"campus_city":"Palermo","duration_years":3,"ects_total":180,"source_url":"https://www.unipa.it","last_checked":"2026-01-05","confidence":0.9,"notes":"Healthcare profession"},
    {"type":"program","university_id":"unipa","degree_level":"bachelor","program_name":"Scienze Nautiche, Aeronautiche e Meteo-Oceanografiche","class_code":"L-28","language":["Italian"],"campus_city":"Palermo","duration_years":3,"ects_total":180,"source_url":"https://www.unipa.it","last_checked":"2026-01-05","confidence":0.9,"notes":"Maritime focus"},
    {"type":"program","university_id":"unipa","degree_level":"bachelor","program_name":"Tecnologie per la Conservazione e il Restauro dei Beni Culturali","class_code":"L-43","language":["Italian"],"campus_city":"Palermo","duration_years":3,"ects_total":180,"source_url":"https://www.unipa.it","last_checked":"2026-01-05","confidence":0.9,"notes":""},
    {"type":"program","university_id":"unipa","degree_level":"bachelor","program_name":"Agroingegneria","class_code":"L-25","language":["Italian"],"campus_city":"Palermo","duration_years":3,"ects_total":180,"source_url":"https://www.unipa.it","last_checked":"2026-01-05","confidence":0.9,"notes":""},
    {"type":"program","university_id":"unipa","degree_level":"bachelor","program_name":"Pianificazione e Progettazione della Città","class_code":"L-21","language":["Italian"],"campus_city":"Palermo","duration_years":3,"ects_total":180,"source_url":"https://www.unipa.it","last_checked":"2026-01-05","confidence":0.9,"notes":""},
    {"type":"program","university_id":"unipa","degree_level":"ciclo_unico","program_name":"Medicina e Chirurgia","class_code":"LM-41","language":["Italian"],"campus_city":"Palermo","duration_years":6,"ects_total":360,"source_url":"https://www.unipa.it","last_checked":"2026-01-05","confidence":0.9,"notes":"Numero programmato nazionale"},
    {"type":"program","university_id":"unipa","degree_level":"ciclo_unico","program_name":"Odontoiatria e Protesi Dentaria","class_code":"LM-46","language":["Italian"],"campus_city":"Palermo","duration_years":6,"ects_total":360,"source_url":"https://www.unipa.it","last_checked":"2026-01-05","confidence":0.9,"notes":"Numero programmato nazionale"},
    {"type":"program","university_id":"unipa","degree_level":"ciclo_unico","program_name":"Giurisprudenza","class_code":"LMG/01","language":["Italian"],"campus_city":"Palermo","duration_years":5,"ects_total":300,"source_url":"https://www.unipa.it","last_checked":"2026-01-05","confidence":0.9,"notes":""},
    {"type":"program","university_id":"unipa","degree_level":"ciclo_unico","program_name":"Giurisprudenza","class_code":"LMG/01","language":["Italian"],"campus_city":"Trapani","duration_years":5,"ects_total":300,"source_url":"https://www.unipa.it","last_checked":"2026-01-05","confidence":0.9,"notes":"Polo Trapani"},
    {"type":"program","university_id":"unipa","degree_level":"ciclo_unico","program_name":"Giurisprudenza","class_code":"LMG/01","language":["Italian"],"campus_city":"Agrigento","duration_years":5,"ects_total":300,"source_url":"https://www.unipa.it","last_checked":"2026-01-05","confidence":0.9,"notes":"Polo Agrigento"},
    {"type":"program","university_id":"unipa","degree_level":"ciclo_unico","program_name":"Scienze della Formazione Primaria","class_code":"LM-85 bis","language":["Italian"],"campus_city":"Palermo","duration_years":5,"ects_total":300,"source_url":"https://www.unipa.it","last_checked":"2026-01-05","confidence":0.9,"notes":"Numero programmato"},
    {"type":"program","university_id":"unipa","degree_level":"ciclo_unico","program_name":"Farmacia","class_code":"LM-13","language":["Italian"],"campus_city":"Palermo","duration_years":5,"ects_total":300,"source_url":"https://www.unipa.it","last_checked":"2026-01-05","confidence":0.9,"notes":""},
    {"type":"program","university_id":"unipa","degree_level":"ciclo_unico","program_name":"Chimica e Tecnologia Farmaceutiche","class_code":"LM-13","language":["Italian"],"campus_city":"Palermo","duration_years":5,"ects_total":300,"source_url":"https://www.unipa.it","last_checked":"2026-01-05","confidence":0.9,"notes":""},
    {"type":"program","university_id":"unipa","degree_level":"ciclo_unico","program_name":"Architettura","class_code":"LM-4 c.u.","language":["Italian"],"campus_city":"Palermo","duration_years":5,"ects_total":300,"source_url":"https://www.unipa.it","last_checked":"2026-01-05","confidence":0.9,"notes":"Numero programmato"},
    {"type":"program","university_id":"unipa","degree_level":"ciclo_unico","program_name":"Conservazione e Restauro dei Beni Culturali","class_code":"LMR/02","language":["Italian"],"campus_city":"Palermo","duration_years":5,"ects_total":300,"source_url":"https://www.unipa.it","last_checked":"2026-01-05","confidence":0.9,"notes":""},
    {"type":"program","university_id":"unipa","degree_level":"master","program_name":"Biologia Molecolare e della Salute","class_code":"LM-6","language":["Italian"],"campus_city":"Palermo","duration_years":2,"ects_total":120,"source_url":"https://www.unipa.it","last_checked":"2026-01-05","confidence":0.9,"notes":""},
    {"type":"program","university_id":"unipa","degree_level":"master","program_name":"Biodiversità e Biologia Ambientale","class_code":"LM-6","language":["Italian"],"campus_city":"Palermo","duration_years":2,"ects_total":120,"source_url":"https://www.unipa.it","last_checked":"2026-01-05","confidence":0.9,"notes":""},
    {"type":"program","university_id":"unipa","degree_level":"master","program_name":"Biotecnologie Mediche e Medicina Molecolare","class_code":"LM-9","language":["Italian"],"campus_city":"Palermo","duration_years":2,"ects_total":120,"source_url":"https://www.unipa.it","last_checked":"2026-01-05","confidence":0.9,"notes":""},
    {"type":"program","university_id":"unipa","degree_level":"master","program_name":"Chimica","class_code":"LM-54","language":["Italian"],"campus_city":"Palermo","duration_years":2,"ects_total":120,"source_url":"https://www.unipa.it","last_checked":"2026-01-05","confidence":0.9,"notes":""},
    {"type":"program","university_id":"unipa","degree_level":"master","program_name":"Fisica","class_code":"LM-17","language":["Italian"],"campus_city":"Palermo","duration_years":2,"ects_total":120,"source_url":"https://www.unipa.it","last_checked":"2026-01-05","confidence":0.9,"notes":""},
    {"type":"program","university_id":"unipa","degree_level":"master","program_name":"Informatica","class_code":"LM-18","language":["Italian"],"campus_city":"Palermo","duration_years":2,"ects_total":120,"source_url":"https://www.unipa.it","last_checked":"2026-01-05","confidence":0.9,"notes":""},
    {"type":"program","university_id":"unipa","degree_level":"master","program_name":"Matematica","class_code":"LM-40","language":["Italian"],"campus_city":"Palermo","duration_years":2,"ects_total":120,"source_url":"https://www.unipa.it","last_checked":"2026-01-05","confidence":0.9,"notes":""},
    {"type":"program","university_id":"unipa","degree_level":"master","program_name":"Scienze della Terra e del Mare","class_code":"LM-74","language":["Italian"],"campus_city":"Palermo","duration_years":2,"ects_total":120,"source_url":"https://www.unipa.it","last_checked":"2026-01-05","confidence":0.9,"notes":""},
    {"type":"program","university_id":"unipa","degree_level":"master","program_name":"Scienze della Natura","class_code":"LM-60","language":["Italian"],"campus_city":"Palermo","duration_years":2,"ects_total":120,"source_url":"https://www.unipa.it","last_checked":"2026-01-05","confidence":0.9,"notes":""},
    {"type":"program","university_id":"unipa","degree_level":"master","program_name":"Scienze Statistiche","class_code":"LM-82","language":["Italian"],"campus_city":"Palermo","duration_years":2,"ects_total":120,"source_url":"https://www.unipa.it","last_checked":"2026-01-05","confidence":0.9,"notes":""},
    {"type":"program","university_id":"unipa","degree_level":"master","program_name":"Economia e Finanza","class_code":"LM-56","language":["Italian"],"campus_city":"Palermo","duration_years":2,"ects_total":120,"source_url":"https://www.unipa.it","last_checked":"2026-01-05","confidence":0.9,"notes":""},
    {"type":"program","university_id":"unipa","degree_level":"master","program_name":"Scienze Economiche e Finanziarie","class_code":"LM-56","language":["Italian"],"campus_city":"Palermo","duration_years":2,"ects_total":120,"source_url":"https://www.unipa.it","last_checked":"2026-01-05","confidence":0.9,"notes":""},
    {"type":"program","university_id":"unipa","degree_level":"master","program_name":"Scienze Economico-Aziendali","class_code":"LM-77","language":["Italian"],"campus_city":"Palermo","duration_years":2,"ects_total":120,"source_url":"https://www.unipa.it","last_checked":"2026-01-05","confidence":0.9,"notes":""},
    {"type":"program","university_id":"unipa","degree_level":"master","program_name":"Tourism Systems and Hospitality Management","class_code":"LM-49","language":["English"],"campus_city":"Palermo","duration_years":2,"ects_total":120,"source_url":"https://www.unipa.it","last_checked":"2026-01-05","confidence":0.9,"notes":"English program"},
    {"type":"program","university_id":"unipa","degree_level":"master","program_name":"Ingegneria Biomedica","class_code":"LM-21","language":["Italian"],"campus_city":"Palermo","duration_years":2,"ects_total":120,"source_url":"https://www.unipa.it","last_checked":"2026-01-05","confidence":0.9,"notes":""},
    {"type":"program","university_id":"unipa","degree_level":"master","program_name":"Ingegneria Chimica","class_code":"LM-22","language":["Italian"],"campus_city":"Palermo","duration_years":2,"ects_total":120,"source_url":"https://www.unipa.it","last_checked":"2026-01-05","confidence":0.9,"notes":""},
    {"type":"program","university_id":"unipa","degree_level":"master","program_name":"Ingegneria Civile","class_code":"LM-23","language":["Italian"],"campus_city":"Palermo","duration_years":2,"ects_total":120,"source_url":"https://www.unipa.it","last_checked":"2026-01-05","confidence":0.9,"notes":""},
    {"type":"program","university_id":"unipa","degree_level":"master","program_name":"Ingegneria dei Sistemi Edilizi","class_code":"LM-24","language":["Italian"],"campus_city":"Palermo","duration_years":2,"ects_total":120,"source_url":"https://www.unipa.it","last_checked":"2026-01-05","confidence":0.9,"notes":""},
    {"type":"program","university_id":"unipa","degree_level":"master","program_name":"Ingegneria Elettrica","class_code":"LM-28","language":["Italian"],"campus_city":"Palermo","duration_years":2,"ects_total":120,"source_url":"https://www.unipa.it","last_checked":"2026-01-05","confidence":0.9,"notes":""},
    {"type":"program","university_id":"unipa","degree_level":"master","program_name":"Ingegneria Elettronica","class_code":"LM-29","language":["Italian"],"campus_city":"Palermo","duration_years":2,"ects_total":120,"source_url":"https://www.unipa.it","last_checked":"2026-01-05","confidence":0.9,"notes":""},
    {"type":"program","university_id":"unipa","degree_level":"master","program_name":"Ingegneria Energetica e Nucleare","class_code":"LM-30","language":["Italian"],"campus_city":"Palermo","duration_years":2,"ects_total":120,"source_url":"https://www.unipa.it","last_checked":"2026-01-05","confidence":0.9,"notes":""},
    {"type":"program","university_id":"unipa","degree_level":"master","program_name":"Ingegneria Gestionale","class_code":"LM-31","language":["Italian"],"campus_city":"Palermo","duration_years":2,"ects_total":120,"source_url":"https://www.unipa.it","last_checked":"2026-01-05","confidence":0.9,"notes":""},
    {"type":"program","university_id":"unipa","degree_level":"master","program_name":"Ingegneria Informatica","class_code":"LM-32","language":["Italian"],"campus_city":"Palermo","duration_years":2,"ects_total":120,"source_url":"https://www.unipa.it","last_checked":"2026-01-05","confidence":0.9,"notes":""},
    {"type":"program","university_id":"unipa","degree_level":"master","program_name":"Ingegneria Meccanica","class_code":"LM-33","language":["Italian"],"campus_city":"Palermo","duration_years":2,"ects_total":120,"source_url":"https://www.unipa.it","last_checked":"2026-01-05","confidence":0.9,"notes":""},
    {"type":"program","university_id":"unipa","degree_level":"master","program_name":"Ingegneria per l'Ambiente e il Territorio","class_code":"LM-35","language":["Italian"],"campus_city":"Palermo","duration_years":2,"ects_total":120,"source_url":"https://www.unipa.it","last_checked":"2026-01-05","confidence":0.9,"notes":""},
    {"type":"program","university_id":"unipa","degree_level":"master","program_name":"Architettura del Paesaggio","class_code":"LM-3","language":["Italian"],"campus_city":"Palermo","duration_years":2,"ects_total":120,"source_url":"https://www.unipa.it","last_checked":"2026-01-05","confidence":0.9,"notes":""},
    {"type":"program","university_id":"unipa","degree_level":"master","program_name":"Pianificazione Territoriale, Urbanistica e Ambientale","class_code":"LM-48","language":["Italian"],"campus_city":"Palermo","duration_years":2,"ects_total":120,"source_url":"https://www.unipa.it","last_checked":"2026-01-05","confidence":0.9,"notes":""},
    {"type":"program","university_id":"unipa","degree_level":"master","program_name":"Design del Sistema Prodotto","class_code":"LM-12","language":["Italian"],"campus_city":"Palermo","duration_years":2,"ects_total":120,"source_url":"https://www.unipa.it","last_checked":"2026-01-05","confidence":0.9,"notes":""},
    {"type":"program","university_id":"unipa","degree_level":"master","program_name":"Filosofia e Scienze dell'Antichità","class_code":"LM-78","language":["Italian"],"campus_city":"Palermo","duration_years":2,"ects_total":120,"source_url":"https://www.unipa.it","last_checked":"2026-01-05","confidence":0.9,"notes":""},
    {"type":"program","university_id":"unipa","degree_level":"master","program_name":"Filologia Moderna e Italianistica","class_code":"LM-14","language":["Italian"],"campus_city":"Palermo","duration_years":2,"ects_total":120,"source_url":"https://www.unipa.it","last_checked":"2026-01-05","confidence":0.9,"notes":""},
    {"type":"program","university_id":"unipa","degree_level":"master","program_name":"Scienze dell'Antichità","class_code":"LM-15","language":["Italian"],"campus_city":"Palermo","duration_years":2,"ects_total":120,"source_url":"https://www.unipa.it","last_checked":"2026-01-05","confidence":0.9,"notes":""},
    {"type":"program","university_id":"unipa","degree_level":"master","program_name":"Storia dell'Arte","class_code":"LM-89","language":["Italian"],"campus_city":"Palermo","duration_years":2,"ects_total":120,"source_url":"https://www.unipa.it","last_checked":"2026-01-05","confidence":0.9,"notes":""},
    {"type":"program","university_id":"unipa","degree_level":"master","program_name":"Archeologia","class_code":"LM-2","language":["Italian"],"campus_city":"Palermo","duration_years":2,"ects_total":120,"source_url":"https://www.unipa.it","last_checked":"2026-01-05","confidence":0.9,"notes":""},
    {"type":"program","university_id":"unipa","degree_level":"master","program_name":"Musicologia e Scienze dello Spettacolo","class_code":"LM-45","language":["Italian"],"campus_city":"Palermo","duration_years":2,"ects_total":120,"source_url":"https://www.unipa.it","last_checked":"2026-01-05","confidence":0.9,"notes":""},
    {"type":"program","university_id":"unipa","degree_level":"master","program_name":"Lingue e Letterature: Interculturalità e Didattica","class_code":"LM-37","language":["Italian"],"campus_city":"Palermo","duration_years":2,"ects_total":120,"source_url":"https://www.unipa.it","last_checked":"2026-01-05","confidence":0.9,"notes":""},
    {"type":"program","university_id":"unipa","degree_level":"master","program_name":"Traduzione, Italiano L2 e Interculturalità","class_code":"LM-94","language":["Italian"],"campus_city":"Palermo","duration_years":2,"ects_total":120,"source_url":"https://www.unipa.it","last_checked":"2026-01-05","confidence":0.9,"notes":""},
    {"type":"program","university_id":"unipa","degree_level":"master","program_name":"Comunicazione del Patrimonio Culturale","class_code":"LM-92","language":["Italian"],"campus_city":"Palermo","duration_years":2,"ects_total":120,"source_url":"https://www.unipa.it","last_checked":"2026-01-05","confidence":0.9,"notes":""},
    {"type":"program","university_id":"unipa","degree_level":"master","program_name":"Mass Media e Politica","class_code":"LM-19","language":["Italian"],"campus_city":"Palermo","duration_years":2,"ects_total":120,"source_url":"https://www.unipa.it","last_checked":"2026-01-05","confidence":0.9,"notes":""},
    {"type":"program","university_id":"unipa","degree_level":"master","program_name":"Psicologia Clinica","class_code":"LM-51","language":["Italian"],"campus_city":"Palermo","duration_years":2,"ects_total":120,"source_url":"https://www.unipa.it","last_checked":"2026-01-05","confidence":0.9,"notes":""},
    {"type":"program","university_id":"unipa","degree_level":"master","program_name":"Psicologia del Ciclo di Vita","class_code":"LM-51","language":["Italian"],"campus_city":"Palermo","duration_years":2,"ects_total":120,"source_url":"https://www.unipa.it","last_checked":"2026-01-05","confidence":0.9,"notes":""},
    {"type":"program","university_id":"unipa","degree_level":"master","program_name":"Psicologia Sociale, del Lavoro e delle Organizzazioni","class_code":"LM-51","language":["Italian"],"campus_city":"Palermo","duration_years":2,"ects_total":120,"source_url":"https://www.unipa.it","last_checked":"2026-01-05","confidence":0.9,"notes":""},
    {"type":"program","university_id":"unipa","degree_level":"master","program_name":"Scienze Pedagogiche","class_code":"LM-85","language":["Italian"],"campus_city":"Palermo","duration_years":2,"ects_total":120,"source_url":"https://www.unipa.it","last_checked":"2026-01-05","confidence":0.9,"notes":""},
    {"type":"program","university_id":"unipa","degree_level":"master","program_name":"Relazioni Internazionali","class_code":"LM-52","language":["Italian"],"campus_city":"Palermo","duration_years":2,"ects_total":120,"source_url":"https://www.unipa.it","last_checked":"2026-01-05","confidence":0.9,"notes":""},
    {"type":"program","university_id":"unipa","degree_level":"master","program_name":"Servizio Sociale e Politiche Sociali","class_code":"LM-87","language":["Italian"],"campus_city":"Palermo","duration_years":2,"ects_total":120,"source_url":"https://www.unipa.it","last_checked":"2026-01-05","confidence":0.9,"notes":""},
    {"type":"program","university_id":"unipa","degree_level":"master","program_name":"Studi Globali. Storia, Politiche e Culture","class_code":"LM-84","language":["Italian"],"campus_city":"Palermo","duration_years":2,"ects_total":120,"source_url":"https://www.unipa.it","last_checked":"2026-01-05","confidence":0.9,"notes":""},
    {"type":"program","university_id":"unipa","degree_level":"master","program_name":"Pubblica Amministrazione","class_code":"LM-63","language":["Italian"],"campus_city":"Palermo","duration_years":2,"ects_total":120,"source_url":"https://www.unipa.it","last_checked":"2026-01-05","confidence":0.9,"notes":""},
    {"type":"program","university_id":"unipa","degree_level":"master","program_name":"Scienze e Tecniche delle Attività Motorie Preventive e Adattate","class_code":"LM-67","language":["Italian"],"campus_city":"Palermo","duration_years":2,"ects_total":120,"source_url":"https://www.unipa.it","last_checked":"2026-01-05","confidence":0.9,"notes":""},
    {"type":"program","university_id":"unipa","degree_level":"master","program_name":"Scienze e Tecniche delle Attività Sportive","class_code":"LM-68","language":["Italian"],"campus_city":"Palermo","duration_years":2,"ects_total":120,"source_url":"https://www.unipa.it","last_checked":"2026-01-05","confidence":0.9,"notes":""},
    {"type":"program","university_id":"unipa","degree_level":"master","program_name":"Scienze e Tecnologie Agrarie","class_code":"LM-69","language":["Italian"],"campus_city":"Palermo","duration_years":2,"ects_total":120,"source_url":"https://www.unipa.it","last_checked":"2026-01-05","confidence":0.9,"notes":""},
    {"type":"program","university_id":"unipa","degree_level":"master","program_name":"Scienze e Tecnologie Alimentari","class_code":"LM-70","language":["Italian"],"campus_city":"Palermo","duration_years":2,"ects_total":120,"source_url":"https://www.unipa.it","last_checked":"2026-01-05","confidence":0.9,"notes":""},
    {"type":"program","university_id":"unipa","degree_level":"master","program_name":"Scienze Forestali e Ambientali","class_code":"LM-73","language":["Italian"],"campus_city":"Palermo","duration_years":2,"ects_total":120,"source_url":"https://www.unipa.it","last_checked":"2026-01-05","confidence":0.9,"notes":""},
    {"type":"program","university_id":"unipa","degree_level":"master","program_name":"Imprenditorialità e Qualità per il Sistema Agroalimentare","class_code":"LM-77","language":["Italian"],"campus_city":"Palermo","duration_years":2,"ects_total":120,"source_url":"https://www.unipa.it","last_checked":"2026-01-05","confidence":0.9,"notes":""},
    {"type":"program","university_id":"unipa","degree_level":"master","program_name":"Mediterranean Food Science and Technology","class_code":"LM-70","language":["English"],"campus_city":"Palermo","duration_years":2,"ects_total":120,"source_url":"https://www.unipa.it","last_checked":"2026-01-05","confidence":0.9,"notes":"English program"},
    {"type":"program","university_id":"unipa","degree_level":"master","program_name":"Scienze Infermieristiche e Ostetriche","class_code":"LM/SNT1","language":["Italian"],"campus_city":"Palermo","duration_years":2,"ects_total":120,"source_url":"https://www.unipa.it","last_checked":"2026-01-05","confidence":0.9,"notes":"Healthcare profession"},
    {"type":"program","university_id":"unipa","degree_level":"master","program_name":"Scienze delle Professioni Sanitarie della Riabilitazione","class_code":"LM/SNT2","language":["Italian"],"campus_city":"Palermo","duration_years":2,"ects_total":120,"source_url":"https://www.unipa.it","last_checked":"2026-01-05","confidence":0.9,"notes":"Healthcare profession"},
    {"type":"program","university_id":"unipa","degree_level":"master","program_name":"Scienze delle Professioni Sanitarie Tecniche Diagnostiche","class_code":"LM/SNT3","language":["Italian"],"campus_city":"Palermo","duration_years":2,"ects_total":120,"source_url":"https://www.unipa.it","last_checked":"2026-01-05","confidence":0.9,"notes":"Healthcare profession"},
    {"type":"program","university_id":"unipa","degree_level":"master","program_name":"Scienze della Nutrizione Umana","class_code":"LM-61","language":["Italian"],"campus_city":"Palermo","duration_years":2,"ects_total":120,"source_url":"https://www.unipa.it","last_checked":"2026-01-05","confidence":0.9,"notes":""}
  ],
  "admissions": [{
    "type":"admissions",
    "university_id":"unipa",
    "program_name":"",
    "degree_level_scope":"general",
    "applicant_scope":"all",
    "requirements":{
      "academic_requirements":"Secondary school diploma for bachelor, bachelor degree for master",
      "documents_required":["Diploma","Identity document","Tax code","ISEE"],
      "tests_required":["TOLC for some programs","National test for Medicine/Dentistry/Architecture"],
      "portfolio_required":false,
      "interview_required":false
    },
    "intakes":[{
      "intake_name":"A.A. 2025/2026",
      "application_open_date":"",
      "application_deadline":"",
      "start_date":"September 2025",
      "notes":"Various deadlines by program"
    }],
    "application_fee":{"amount":16,"currency":"EUR","notes":"Stamp duty"},
    "how_to_apply_url":"https://www.unipa.it/target/futuristudenti/",
    "source_url":"https://www.unipa.it",
    "last_checked":"2026-01-05",
    "confidence":0.95,
    "notes":"Some programs have numbered access (numero programmato). Medicine, Architecture require national tests."
  }],
  "tuition": [{
    "type":"tuition",
    "university_id":"unipa",
    "program_name":"",
    "degree_level_scope":"general",
    "tuition":[
      {"student_group":"ISEE 0-25,000 (No Tax Area)","amount_min":156,"amount_max":156,"currency":"EUR","period":"year","notes":"Only regional tax €140 + stamp €16"},
      {"student_group":"ISEE 25,001-40,000","amount_min":156,"amount_max":1200,"currency":"EUR","period":"year","notes":"Progressive scale"},
      {"student_group":"ISEE 40,001-70,000","amount_min":1200,"amount_max":2000,"currency":"EUR","period":"year","notes":"Progressive scale"},
      {"student_group":"ISEE >70,000 or no ISEE","amount_min":2000,"amount_max":2500,"currency":"EUR","period":"year","notes":"Maximum rate"},
      {"student_group":"Disability ≥66% or L.104","amount_min":0,"amount_max":0,"currency":"EUR","period":"year","notes":"Full exemption"}
    ],
    "additional_fees":[
      {"fee_name":"Regional DSU tax","amount":140,"currency":"EUR","notes":"Always required unless scholarship winner"},
      {"fee_name":"Stamp duty","amount":16,"currency":"EUR","notes":"Always required"}
    ],
    "payment_schedule_notes":"Three installments: 1st (40%) at enrollment, 2nd (30%) by Dec 31, 3rd (30%) by Feb 28.",
    "source_url":"https://www.unipa.it/No-Tax-Area/",
    "last_checked":"2026-01-05",
    "confidence":0.95,
    "notes":"No tax area €25,000. Merit requirements from 2nd year: 10 CFU by Aug 10 (yr 2), 25 CFU in 12 months (subsequent)."
  }],
  "scholarships": [
    {
      "type":"scholarships",
      "university_id":"unipa",
      "scholarship_name":"ERSU Palermo Regional Scholarship",
      "description":"Regional scholarship covering tuition and living expenses",
      "eligibility":"ISEE ≤ €26,306.25, ISPE requirements, merit requirements",
      "amount":{"min":2000,"max":5500,"currency":"EUR","period":"year"},
      "deadline":"July 2025",
      "how_to_apply_url":"https://www.ersupalermo.it",
      "source_url":"https://www.unipa.it",
      "last_checked":"2026-01-05",
      "confidence":0.9,
      "notes":"Includes tuition exemption, monthly stipend, housing and meal service options"
    },
    {
      "type":"scholarships",
      "university_id":"unipa",
      "scholarship_name":"Maturità Excellence Awards",
      "description":"Merit-based fee reduction for top high school graduates",
      "eligibility":"100/100 or 100 e lode at maturità",
      "amount":{"min":null,"max":null,"currency":"EUR","period":"year"},
      "deadline":"At enrollment",
      "how_to_apply_url":"https://www.unipa.it",
      "source_url":"https://www.unipa.it",
      "last_checked":"2026-01-05",
      "confidence":0.85,
      "notes":"Fee reductions for students with excellent high school results"
    }
  ],
  "opportunities": []
}
